simple_stat_learning/__init__.py
simple_stat_learning/assumptions.py
simple_stat_learning/model_inference.py
simple_stat_learning/models.py
simple_stat_learning/preprocessing.py
simple_stat_learning-0.1.0.dist-info/WHEEL
simple_stat_learning-0.1.0.dist-info/METADATA
simple_stat_learning-0.1.0.dist-info/RECORD
