Metadata-Version: 2.1
Name: simple-stat-learning
Version: 0.1.0
Summary: 
Author: Your Name
Author-email: you@example.com
Requires-Python: >=3.7,<4.0
Classifier: Programming Language :: Python :: 3
Classifier: Programming Language :: Python :: 3.7
Classifier: Programming Language :: Python :: 3.8
Requires-Dist: matplotlib (>=3.1.2,<4.0.0)
Requires-Dist: numpy (>=1.18.1,<2.0.0)
Requires-Dist: seaborn (>=0.10.0,<0.11.0)
